dropdown_filters/__init__.py
dropdown_filters/admin.py
dropdown_filters/apps.py
dropdown_filters/filters.py
dropdown_filters/models.py
dropdown_filters/migrations/__init__.py
dropdown_filters-1.0.dist-info/LICENSE
dropdown_filters-1.0.dist-info/METADATA
dropdown_filters-1.0.dist-info/WHEEL
dropdown_filters-1.0.dist-info/top_level.txt
dropdown_filters-1.0.dist-info/RECORD
