Metadata-Version: 2.1
Name: dropdown-filters
Version: 1.0
Summary: Reusable Django admin filters
Home-page: https://github.com/DiegoP2001/Dropdown_filters
Author: Diego Piedra
Author-email: diego@dieveloper.com
License: UNKNOWN
Platform: UNKNOWN
Classifier: Programming Language :: Python :: 3
Classifier: Framework :: Django
Classifier: Operating System :: OS Independent
Requires-Dist: Django>=2.0.8
